libproton/__init__.py
libproton/program.py
libproton/proton_helper.py
tests/__init__.py
tests/helpers.py
tests/tests_cli.py
tests/tests_program.py
tests/tests_proton_helper.py
libproton-3.3.dist-info/LICENSE
libproton-3.3.dist-info/METADATA
libproton-3.3.dist-info/WHEEL
libproton-3.3.dist-info/top_level.txt
libproton-3.3.dist-info/zip-safe
libproton-3.3.dist-info/RECORD
