Metadata-Version: 2.1
Name: libproton
Version: 3.3
Summary: Proton-compliant match scorer library.
Home-page: https://github.com/PeterJCLaw/libproton
Author: Peter Law
Author-email: PeterJCLaw@gmail.com
License: MIT
Project-URL: Issue tracker, https://github.com/PeterJCLaw/libproton/issues
Classifier: Development Status :: 5 - Production/Stable
Classifier: Environment :: Console
Classifier: Natural Language :: English
Classifier: Operating System :: OS Independent
Classifier: Programming Language :: Python
Classifier: Programming Language :: Python :: 3
Classifier: Programming Language :: Python :: 3.7
Classifier: Programming Language :: Python :: 3.8
Classifier: Programming Language :: Python :: 3.9
Classifier: Programming Language :: Python :: 3.10
Classifier: Programming Language :: Python :: 3.11
Classifier: Programming Language :: Python :: 3.12
Requires-Python: >=3.7
License-File: LICENSE
Requires-Dist: PyYAML <7,>=3.11
